tituemg/__init__.py
tituemg/emg.py
tituemg-0.0.1.4.dist-info/LICENSE
tituemg-0.0.1.4.dist-info/METADATA
tituemg-0.0.1.4.dist-info/WHEEL
tituemg-0.0.1.4.dist-info/top_level.txt
tituemg-0.0.1.4.dist-info/RECORD
