Metadata-Version: 2.1
Name: tituemg
Version: 0.0.1.4
Summary: Heramioentas utiles para el proceso de EMG
Home-page: https://github.com/tistu37/tituemg
Author: Tomas Tubino
Author-email: titubino@miuandes.cl.com
Classifier: Programming Language :: Python :: 3
Classifier: License :: OSI Approved :: MIT License
Classifier: Operating System :: OS Independent
Requires-Python: >=3.6
License-File: LICENSE
Requires-Dist: scipy
Requires-Dist: numpy
